hello2468/__init__.py
hello2468-0.1.2.dist-info/licenses/LICENSE
hello2468-0.1.2.dist-info/METADATA
hello2468-0.1.2.dist-info/WHEEL
hello2468-0.1.2.dist-info/top_level.txt
hello2468-0.1.2.dist-info/RECORD
