Metadata-Version: 2.4
Name: hello2468
Version: 0.1.2
Summary: A hello world package for demonstration
Author-email: Utsav Savaliya <utsav.savaliya@pattern.com>
License: MIT
Project-URL: Homepage, https://github.com/Utsav1973/hello2468
Requires-Python: >=3.10
License-File: LICENSE
Dynamic: license-file
